MUX8to1.v
module MUX8to1 (
	input s0,
	input s1, 
	input s2,
	input a,
	input b,
	input c,
	input d,
	input e,
	input f,
	input g,
	input h,
	output y
);

reg y;

always @(s1 or s2) 
begin 
	case ({s0, s1, s2})

		3'b000 : begin 
					 assign y = a;
				  end

		3'b001 : begin 
					 assign y = b;
				  end

		3'b010 : begin 
					 assign y = c;
				  end

		3'b011 : begin 
					 assign y = d;
				  end

		3'b100 : begin 
					 assign y = e;
				  end

		3'b101 : begin 
					 assign y = f;
				  end

		3'b110 : begin 
					 assign y = g;
				  end

		3'b111 : begin 
					 assign y = h;
				  end
	
		default : assign y = 1'b0;
	endcase
end

endmodule

MUX8to1_tb.v
`timescale 1s/100ms
`include "MUX8to1.v"

module MUX8to1_tb();
	reg s0;
	reg s1;
	reg s2;
	reg a;
	reg b;
	reg c;
	reg d;
	reg e;
	reg f;
	reg g;
	reg h;
	wire y;

	MUX8to1 myMUX(s0, s1, s2, a, b, c, d, e, f, g, h, y);

	initial
	begin 
		a = 1;
		b = 0;
		c = 1;
		d = 0;
		e = 1;
		f = 0;
		g = 1;
		h = 0;
		$monitor("s0 = %b, s1 = %b, s2 = %b, y = %b", s0, s1, s2, y);
		$dumpfile ("MUX8to1.vcd");
		$dumpvars (0, MUX8to1_tb);
		s0 = 0; s1 = 0; s2 = 0; #1;
		s0 = 0; s1 = 0; s2 = 1; #1;
		s0 = 0; s1 = 1; s2 = 0; #1;
		s0 = 0; s1 = 1; s2 = 1; #1;
		s0 = 1; s1 = 0; s2 = 0; #1;
		s0 = 1; s1 = 0; s2 = 1; #1;
		s0 = 1; s1 = 1; s2 = 0; #1;
		s0 = 1; s1 = 1; s2 = 1; #1;
		$finish;
	end
endmodule

MUX8to1.vcd
$date
	Mon Nov 12 09:59:42 2018
$end
$version
	Icarus Verilog
$end
$timescale
	100ms
$end
$scope module MUX8to1_tb $end
$var wire 1 ! y $end
$var reg 1 " a $end
$var reg 1 # b $end
$var reg 1 $ c $end
$var reg 1 % d $end
$var reg 1 & e $end
$var reg 1 ' f $end
$var reg 1 ( g $end
$var reg 1 ) h $end
$var reg 1 * s0 $end
$var reg 1 + s1 $end
$var reg 1 , s2 $end
$scope module myMUX $end
$var wire 1 " a $end
$var wire 1 # b $end
$var wire 1 $ c $end
$var wire 1 % d $end
$var wire 1 & e $end
$var wire 1 ' f $end
$var wire 1 ( g $end
$var wire 1 ) h $end
$var wire 1 * s0 $end
$var wire 1 + s1 $end
$var wire 1 , s2 $end
$var reg 1 ! y $end
$upscope $end
$upscope $end
$enddefinitions $end
#0
$dumpvars
0,
0+
0*
0)
1(
0'
1&
0%
1$
0#
1"
1!
$end
#10
0!
1,
#20
1!
0,
1+
#30
0!
1,
#40
1!
0,
0+
1*
#50
0!
1,
#60
1!
0,
1+
#70
0!
1,
